{
  "team": "alpha",
  "cycle": 8,
  "duration_minutes": 30,
  "timestamp": "2026-04-09T04:32:36.135821+00:00",
  "total_trades": 7,
  "win_count": 2,
  "win_rate": 28.57,
  "total_pnl": -0.067945,
  "avg_pnl": -0.009706,
  "best_trade": 0.095385,
  "worst_trade": -0.063076,
  "profit_factor": 0.6346,
  "total_fees": 0.025333,
  "net_pnl": -0.067945,
  "open_positions": 0,
  "symbols_traded": [
    "OPNUSDT",
    "CFGUSDT",
    "PRLUSDT",
    "XAGUSDT",
    "EDGEUSDT"
  ],
  "symbols_count": 5
}